README.rst
setup.py
zenoss_hipchat/__init__.py
zenoss_hipchat/command.py
zenoss_hipchat/config.py
zenoss_hipchat/hipchat.py
zenoss_hipchat.egg-info/PKG-INFO
zenoss_hipchat.egg-info/SOURCES.txt
zenoss_hipchat.egg-info/dependency_links.txt
zenoss_hipchat.egg-info/entry_points.txt
zenoss_hipchat.egg-info/requires.txt
zenoss_hipchat.egg-info/top_level.txt
zenoss_hipchat.egg-info/zip-safe