Metadata-Version: 1.1
Name: zenoss-hipchat
Version: 0.2.0
Summary: Command suitable in use for Zenoss notification commands for sending events to hipchat.
Home-page: http://github.com/carsongee/zenoss-hipchat
Author: Carson Gee
Author-email: x@carsongee.com
License: GPLv3
Platform: UNKNOWN
Classifier: Development Status :: 2 - Pre-Alpha
Classifier: Intended Audience :: Information Technology
Classifier: License :: OSI Approved :: GNU Lesser General Public License v3 (LGPLv3)
Classifier: Operating System :: POSIX :: Linux
